color/__init__.py
color/darwin_linux.py
color/windows.py
sboh_py-0.1.dist-info/METADATA
sboh_py-0.1.dist-info/WHEEL
sboh_py-0.1.dist-info/top_level.txt
sboh_py-0.1.dist-info/RECORD
