Metadata-Version: 2.1
Name: sboh-py
Version: 0.1
Summary: Python Utilities
Home-page: https://github.com/sboh1214/sboh_py
Author: Seungbin Oh
Author-email: sboh1214@gmail.com
License: UNKNOWN
Keywords: color,print
Platform: UNKNOWN
Requires-Python: >=3
